{"anlg_tran_data": [{"sub_prob_n": 2, "prob_name": "e6", "anlg_name": "F:G::H:C:::C:D::E:?", "tran_name": "xor_diff", "prob_type": "3x3", "anlg_type": "unary_3x3", "tran_type": "unary", "mat_score": 0.8845003983591591, "prob_ansr": 5, "anlg_grp": 3, "tran_grp": 1}], "pred_data": [{"prob_name": "e6", "anlg_name": "F:G::H:C:::C:D::E:?", "tran_name": "xor_diff", "mat_score": 0.8845003983591591, "prob_ansr": 5, "prob_type": "3x3", "anlg_type": "unary_3x3", "tran_type": "unary", "anlg_grp": 3, "tran_grp": 1, "b1_to_b2_x": null, "b1_to_b2_y": null, "copies_to_u1_x": null, "copies_to_u1_y": null, "u1_coms_x": null, "u1_coms_y": null, "u2_coms_x": null, "u2_coms_y": null, "diff_to_b3_x": null, "diff_to_b3_y": null, "diff_to_b2_x": null, "diff_to_b2_y": null, "optn": 1, "optn_score": 0.4518072601100926, "mato_score": 0.7763271137968926}, {"prob_name": "e6", "anlg_name": "F:G::H:C:::C:D::E:?", "tran_name": "xor_diff", "mat_score": 0.8845003983591591, "prob_ansr": 5, "prob_type": "3x3", "anlg_type": "unary_3x3", "tran_type": "unary", "anlg_grp": 3, "tran_grp": 1, "b1_to_b2_x": null, "b1_to_b2_y": null, "copies_to_u1_x": null, "copies_to_u1_y": null, "u1_coms_x": null, "u1_coms_y": null, "u2_coms_x": null, "u2_coms_y": null, "diff_to_b3_x": null, "diff_to_b3_y": null, "diff_to_b2_x": null, "diff_to_b2_y": null, "optn": 2, "optn_score": 0.20496274067962036, "mato_score": 0.7146159839392745}, {"prob_name": "e6", "anlg_name": "F:G::H:C:::C:D::E:?", "tran_name": "xor_diff", "mat_score": 0.8845003983591591, "prob_ansr": 5, "prob_type": "3x3", "anlg_type": "unary_3x3", "tran_type": "unary", "anlg_grp": 3, "tran_grp": 1, "b1_to_b2_x": null, "b1_to_b2_y": null, "copies_to_u1_x": null, "copies_to_u1_y": null, "u1_coms_x": null, "u1_coms_y": null, "u2_coms_x": null, "u2_coms_y": null, "diff_to_b3_x": null, "diff_to_b3_y": null, "diff_to_b2_x": null, "diff_to_b2_y": null, "optn": 3, "optn_score": 0.48965376247799813, "mato_score": 0.785788739388869}, {"prob_name": "e6", "anlg_name": "F:G::H:C:::C:D::E:?", "tran_name": "xor_diff", "mat_score": 0.8845003983591591, "prob_ansr": 5, "prob_type": "3x3", "anlg_type": "unary_3x3", "tran_type": "unary", "anlg_grp": 3, "tran_grp": 1, "b1_to_b2_x": null, "b1_to_b2_y": null, "copies_to_u1_x": null, "copies_to_u1_y": null, "u1_coms_x": null, "u1_coms_y": null, "u2_coms_x": null, "u2_coms_y": null, "diff_to_b3_x": null, "diff_to_b3_y": null, "diff_to_b2_x": null, "diff_to_b2_y": null, "optn": 4, "optn_score": 0.23091889105287478, "mato_score": 0.721105021532588}, {"prob_name": "e6", "anlg_name": "F:G::H:C:::C:D::E:?", "tran_name": "xor_diff", "mat_score": 0.8845003983591591, "prob_ansr": 5, "prob_type": "3x3", "anlg_type": "unary_3x3", "tran_type": "unary", "anlg_grp": 3, "tran_grp": 1, "b1_to_b2_x": null, "b1_to_b2_y": null, "copies_to_u1_x": null, "copies_to_u1_y": null, "u1_coms_x": null, "u1_coms_y": null, "u2_coms_x": null, "u2_coms_y": null, "diff_to_b3_x": null, "diff_to_b3_y": null, "diff_to_b2_x": null, "diff_to_b2_y": null, "optn": 5, "optn_score": 0.5412419001252845, "mato_score": 0.7986857738006905}, {"prob_name": "e6", "anlg_name": "F:G::H:C:::C:D::E:?", "tran_name": "xor_diff", "mat_score": 0.8845003983591591, "prob_ansr": 5, "prob_type": "3x3", "anlg_type": "unary_3x3", "tran_type": "unary", "anlg_grp": 3, "tran_grp": 1, "b1_to_b2_x": null, "b1_to_b2_y": null, "copies_to_u1_x": null, "copies_to_u1_y": null, "u1_coms_x": null, "u1_coms_y": null, "u2_coms_x": null, "u2_coms_y": null, "diff_to_b3_x": null, "diff_to_b3_y": null, "diff_to_b2_x": null, "diff_to_b2_y": null, "optn": 6, "optn_score": 0.42102551967924545, "mato_score": 0.7686316786891807}, {"prob_name": "e6", "anlg_name": "F:G::H:C:::C:D::E:?", "tran_name": "xor_diff", "mat_score": 0.8845003983591591, "prob_ansr": 5, "prob_type": "3x3", "anlg_type": "unary_3x3", "tran_type": "unary", "anlg_grp": 3, "tran_grp": 1, "b1_to_b2_x": null, "b1_to_b2_y": null, "copies_to_u1_x": null, "copies_to_u1_y": null, "u1_coms_x": null, "u1_coms_y": null, "u2_coms_x": null, "u2_coms_y": null, "diff_to_b3_x": null, "diff_to_b3_y": null, "diff_to_b2_x": null, "diff_to_b2_y": null, "optn": 7, "optn_score": 0.3780152544169803, "mato_score": 0.7578791123736144}, {"prob_name": "e6", "anlg_name": "F:G::H:C:::C:D::E:?", "tran_name": "xor_diff", "mat_score": 0.8845003983591591, "prob_ansr": 5, "prob_type": "3x3", "anlg_type": "unary_3x3", "tran_type": "unary", "anlg_grp": 3, "tran_grp": 1, "b1_to_b2_x": null, "b1_to_b2_y": null, "copies_to_u1_x": null, "copies_to_u1_y": null, "u1_coms_x": null, "u1_coms_y": null, "u2_coms_x": null, "u2_coms_y": null, "diff_to_b3_x": null, "diff_to_b3_y": null, "diff_to_b2_x": null, "diff_to_b2_y": null, "optn": 8, "optn_score": 0.4092244397116685, "mato_score": 0.7656814086972865}], "pred_d": {"prob_name": "e6", "anlg_name": "F:G::H:C:::C:D::E:?", "tran_name": "xor_diff", "mat_score": 0.8845003983591591, "prob_ansr": 5, "prob_type": "3x3", "anlg_type": "unary_3x3", "tran_type": "unary", "anlg_grp": 3, "tran_grp": 1, "diff_to_u1_x": 0, "diff_to_u1_y": 0, "diff_to_u2_x": 0, "diff_to_u2_y": 0, "b1_to_b2_x": null, "b1_to_b2_y": null, "copies_to_u1_x": null, "copies_to_u1_y": null, "u1_coms_x": null, "u1_coms_y": null, "u2_coms_x": null, "u2_coms_y": null, "diff_to_b3_x": null, "diff_to_b3_y": null, "diff_to_b2_x": null, "diff_to_b2_y": null, "optn": 5, "optn_score": 0.5412419001252845, "mato_score": 0.7986857738006905}}